ragnarok/__init__.py
ragnarok/data.py
ragnarok/retrieve_and_generate.py
ragnarok/analyze/__init__.py
ragnarok/api/__init__.py
ragnarok/api/server.py
ragnarok/api/web_server.py
ragnarok/demo/__init__.py
ragnarok/demo/rag_inline_hits.py
ragnarok/demo/rerank_stored_retrieved_results.py
ragnarok/evaluate/__init__.py
ragnarok/generate/__init__.py
ragnarok/generate/api_keys.py
ragnarok/generate/cohere.py
ragnarok/generate/generator.py
ragnarok/generate/gpt.py
ragnarok/generate/llm.py
ragnarok/generate/os_llm.py
ragnarok/generate/post_processor.py
ragnarok/generate/templates/__init__.py
ragnarok/generate/templates/chat_qa.py
ragnarok/retrieve_and_rerank/__init__.py
ragnarok/retrieve_and_rerank/indices_dict.py
ragnarok/retrieve_and_rerank/repo_info.py
ragnarok/retrieve_and_rerank/restriever.py
ragnarok/retrieve_and_rerank/retriever.py
ragnarok/retrieve_and_rerank/topics_dict.py
ragnarok/scripts/__init__.py
ragnarok/scripts/query_cache.py
ragnarok/scripts/run_ragnarok.py
pyragnarok-0.0.1.dist-info/LICENSE
pyragnarok-0.0.1.dist-info/METADATA
pyragnarok-0.0.1.dist-info/WHEEL
pyragnarok-0.0.1.dist-info/top_level.txt
pyragnarok-0.0.1.dist-info/RECORD
