Metadata-Version: 2.1
Name: pyragnarok
Version: 0.0.1
Summary: A package to running RAG models, especially for the TREC 2023 Retrieval Augmented Generation (RAG) track.
Author-email: Ronak Pradeep <rpradeep@uwaterloo.ca>
License: 
Project-URL: Homepage, https://github.com/castorini/ragnarok
Keywords: Retrieval-Augmented Generation,RAG,OpenAI,Cohere,TREC,LLM
Classifier: Programming Language :: Python
Classifier: Programming Language :: Python :: 3
Provides: ragnarok
Requires-Python: >=3.10
License-File: LICENSE
Requires-Dist: tqdm >=4.66.2
Requires-Dist: openai >=1.30.5
Requires-Dist: cohere >=5.3.4
Requires-Dist: tiktoken >=0.6.0
Requires-Dist: transformers >=4.40.1
Requires-Dist: python-dotenv >=1.0.1
Requires-Dist: ftfy >=6.2.0
Requires-Dist: dacite >=1.8.1
Requires-Dist: fschat[model_worker] >=0.2.36
Requires-Dist: stanza >=1.8.2
Requires-Dist: gradio ==4.26.0
Requires-Dist: vllm >=0.4.3
Requires-Dist: spacy ==3.7.2
